README.rst
setup.cfg
setup.py
charlesbot_broadcast_message/__init__.py
charlesbot_broadcast_message/broadcast_message.py
charlesbot_broadcast_message.egg-info/PKG-INFO
charlesbot_broadcast_message.egg-info/SOURCES.txt
charlesbot_broadcast_message.egg-info/dependency_links.txt
charlesbot_broadcast_message.egg-info/not-zip-safe
charlesbot_broadcast_message.egg-info/requires.txt
charlesbot_broadcast_message.egg-info/top_level.txt