Metadata-Version: 1.1
Name: charlesbot-broadcast-message
Version: 0.2.2
Summary: Charlesbot Broadcast Message Plugin
Home-page: https://github.com/marvinpinto/charlesbot-broadcast-message
Author: Marvin Pinto
Author-email: marvin@pinto.im
License: MIT
Keywords: slack robot chatops charlesbot charlesbot-broadcast-message
Platform: UNKNOWN
Classifier: Development Status :: 3 - Alpha
Classifier: Intended Audience :: Developers
Classifier: License :: OSI Approved :: MIT License
Classifier: Programming Language :: Python :: 3.4
